verificado/__init__.py
verificado/__main__.py
verificado/conf/__init__.py
verificado/conf/obograph-style.json
verificado/utils/__init__.py
verificado/utils/utils.py
verificado/validator.py
verificado-1.0.dist-info/LICENSE
verificado-1.0.dist-info/METADATA
verificado-1.0.dist-info/WHEEL
verificado-1.0.dist-info/entry_points.txt
verificado-1.0.dist-info/RECORD
