Metadata-Version: 2.1
Name: verificado
Version: 1.0
Summary: This package validates a list of relationships between two terms against the specified ontologies.
Home-page: https://github.com/INCATools/verificado
Author: Anita Caron
Author-email: anitac@ebi.ac.uk
Requires-Python: >=3.8,<4.0
Classifier: Programming Language :: Python :: 3
Classifier: Programming Language :: Python :: 3.8
Classifier: Programming Language :: Python :: 3.9
Classifier: Programming Language :: Python :: 3.10
Classifier: Programming Language :: Python :: 3.11
Requires-Dist: oaklib (>=0.5.20,<0.6.0)
Requires-Dist: pyaml (>=21.10.1,<22.0.0)
Requires-Dist: ruamel-yaml (>=0.17.21,<0.18.0)
Project-URL: Repository, https://github.com/INCATools/verificado
